{
  "project_info": {
    "project_number": "76549921908",
    "firebase_url": "https://fworld-3c022.firebaseio.com",
    "project_id": "fworld-3c022",
    "storage_bucket": "fworld-3c022.appspot.com"
  },
  "client": [
    {
      "client_info": {
        "mobilesdk_app_id": "1:76549921908:android:43648dabba31b2f9",
        "android_client_info": {
          "package_name": "com.example.fwprld"
        }
      },
      "oauth_client": [
        {
          "client_id": "76549921908-1mckfk14j9o6p6kda7s98jncco34odsa.apps.googleusercontent.com",
          "client_type": 1,
          "android_info": {
            "package_name": "com.example.fwprld",
            "certificate_hash": "f1e5eb6f5190c7fc931ec84f13003e6bc5a74ab9"
          }
        },
        {
          "client_id": "76549921908-d8d06nqrpar9pihr9edfliet824h0d47.apps.googleusercontent.com",
          "client_type": 3
        }
      ],
      "api_key": [
        {
          "current_key": "AIzaSyAlXBHMYN1ePbJXdTvlAx9XKeZgaT7jBW4"
        }
      ],
      "services": {
        "appinvite_service": {
          "other_platform_oauth_client": [
            {
              "client_id": "76549921908-l9gv2l7m5usdo4gofsotg0joduluq8ns.apps.googleusercontent.com",
              "client_type": 3
            }
          ]
        }
      }
    }
  ],
  "configuration_version": "1"
}